diffuse/__init__.py
diffuse/diffuse.py
diffuse/girepo.py
diffuse/main.py
diffuse/preferences.py
diffuse/resources.py
diffuse/ui.py
diffuse/util.py
diffuse/vcs.py
diffuse/viewer/__init__.py
diffuse/viewer/model.py
diffuse/viewer/patience.py
diffuse/viewer/undo.py
diffuse/viewer/util.py
diffuse/viewer/viewer.py
leytonium/__init__.py
leytonium/abandon.py
leytonium/afternet.arid
leytonium/afternet.py
leytonium/agi.py
leytonium/agil.py
leytonium/autokb.arid
leytonium/autokb.py
leytonium/autopull.py
leytonium/awslogs.py
leytonium/bashrc.arid
leytonium/bashrc.py
leytonium/br.py
leytonium/brown.arid
leytonium/brown.py
leytonium/ci.py
leytonium/co.py
leytonium/common.py
leytonium/d.py
leytonium/delegate.py
leytonium/dp.py
leytonium/drclean.bash
leytonium/drclean.py
leytonium/drop.bash
leytonium/drop.py
leytonium/drst.py
leytonium/dup.py
leytonium/dx.py
leytonium/eb.bash
leytonium/eb.py
leytonium/encrypt.arid
leytonium/encrypt.py
leytonium/examine.bash
leytonium/examine.py
leytonium/extractaudio.py
leytonium/fetchall.py
leytonium/fixemails.bash
leytonium/fixemails.py
leytonium/gag.py
leytonium/gimports.bash
leytonium/gimports.py
leytonium/git_completion.bash
leytonium/git_functions.bash
leytonium/git_functions_path.py
leytonium/gpgedit.arid
leytonium/gpgedit.py
leytonium/gt.py
leytonium/halp.arid
leytonium/halp.py
leytonium/hgcommit.py
leytonium/imgdiff.arid
leytonium/imgdiff.py
leytonium/isotime.arid
leytonium/isotime.py
leytonium/ks.py
leytonium/mdview.bash
leytonium/mdview.py
leytonium/multimerge.py
leytonium/n.py
leytonium/ncswitch.arid
leytonium/ncswitch.py
leytonium/next.py
leytonium/pb.py
leytonium/pd.py
leytonium/pinswitch.py
leytonium/prepare.py
leytonium/publish.py
leytonium/pullall.py
leytonium/pushall.py
leytonium/rd.py
leytonium/rdx.py
leytonium/readjust.py
leytonium/reks.bash
leytonium/reks.py
leytonium/ren.py
leytonium/resimp.py
leytonium/rol.py
leytonium/rx.py
leytonium/scrape85.py
leytonium/scrub.py
leytonium/setparent.py
leytonium/shove.py
leytonium/show.py
Leytonium-24.dist-info/COPYING
Leytonium-24.dist-info/METADATA
Leytonium-24.dist-info/WHEEL
Leytonium-24.dist-info/entry_points.txt
Leytonium-24.dist-info/top_level.txt
Leytonium-24.dist-info/RECORD
