Metadata-Version: 2.1
Name: Leytonium
Version: 24
Summary: Tools for developing git-managed software
Home-page: https://github.com/combatopera/Leytonium
Author: Andrzej Cichocki
Author-email: 3613868+combatopera@users.noreply.github.com
License-File: COPYING
Requires-Dist: aridity>=73
Requires-Dist: autopep8>=1.5.4
Requires-Dist: awscli>=1.19.53
Requires-Dist: docutils>=0.15.2
Requires-Dist: foyndation>=12
Requires-Dist: lagoon>=56
Requires-Dist: PyGObject<3.52.1,>=3.42.2
Requires-Dist: pytz>=2020.4
Requires-Dist: pyven>=90
Requires-Dist: PyYAML>=5.2
Requires-Dist: roman>=5
Requires-Dist: setuptools>=44.1.1
Requires-Dist: termcolor>=1.1.0
Requires-Dist: Unidecode>=1.3.2
Requires-Dist: venvpool>=19
